// class version 46.0 (46)
// access flags 0x1
public class com/java/core/proxy/cglib/RealSubject$$EnhancerByCGLIB$$be39b9b5$$FastClassByCGLIB$$c10341e8 extends net/sf/cglib/reflect/FastClass  {

  // compiled from: <generated>

  // access flags 0x1
  public <init>(Ljava/lang/Class;)V
    ALOAD 0
    ALOAD 1
    INVOKESPECIAL net/sf/cglib/reflect/FastClass.<init> (Ljava/lang/Class;)V
    RETURN
    MAXSTACK = 2
    MAXLOCALS = 2

  // access flags 0x1
  public getIndex(Lnet/sf/cglib/core/Signature;)I
    ALOAD 1
    INVOKEVIRTUAL java/lang/Object.toString ()Ljava/lang/String;
    DUP
    INVOKEVIRTUAL java/lang/Object.hashCode ()I
    LOOKUPSWITCH
      -2071771415: L0
      -2055565910: L1
      -1928737044: L2
      -1725733088: L3
      -1663710620: L4
      -1457535688: L5
      -1411783143: L6
      -1026001249: L7
      -894172689: L8
      -623122092: L9
      -419626537: L10
      -59693763: L11
      243996900: L12
      560567118: L13
      811063227: L14
      946854621: L15
      973717575: L16
      1116248544: L17
      1221173700: L18
      1230699260: L19
      1365107430: L20
      1584330438: L21
      1729170762: L22
      1826985398: L23
      1902039948: L24
      1911978376: L25
      1913648695: L26
      1984935277: L27
      2067235672: L28
      default: L29
   L0
    LDC "CGLIB$clone$6()Ljava/lang/Object;"
    INVOKEVIRTUAL java/lang/Object.equals (Ljava/lang/Object;)Z
    IFEQ L30
    BIPUSH 22
    IRETURN
   L1
    LDC "CGLIB$SET_THREAD_CALLBACKS([Lnet/sf/cglib/proxy/Callback;)V"
    INVOKEVIRTUAL java/lang/Object.equals (Ljava/lang/Object;)Z
    IFEQ L30
    BIPUSH 8
    IRETURN
   L2
    LDC "showSelf()V"
    INVOKEVIRTUAL java/lang/Object.equals (Ljava/lang/Object;)Z
    IFEQ L30
    BIPUSH 11
    IRETURN
   L3
    LDC "getClass()Ljava/lang/Class;"
    INVOKEVIRTUAL java/lang/Object.equals (Ljava/lang/Object;)Z
    IFEQ L30
    BIPUSH 26
    IRETURN
   L4
    LDC "CGLIB$equals$3(Ljava/lang/Object;)Z"
    INVOKEVIRTUAL java/lang/Object.equals (Ljava/lang/Object;)Z
    IFEQ L30
    BIPUSH 19
    IRETURN
   L5
    LDC "CGLIB$STATICHOOK1()V"
    INVOKEVIRTUAL java/lang/Object.equals (Ljava/lang/Object;)Z
    IFEQ L30
    BIPUSH 15
    IRETURN
   L6
    LDC "CGLIB$hashCode$5()I"
    INVOKEVIRTUAL java/lang/Object.equals (Ljava/lang/Object;)Z
    IFEQ L30
    BIPUSH 21
    IRETURN
   L7
    LDC "wait(JI)V"
    INVOKEVIRTUAL java/lang/Object.equals (Ljava/lang/Object;)Z
    IFEQ L30
    BIPUSH 23
    IRETURN
   L8
    LDC "newInstance(Lnet/sf/cglib/proxy/Callback;)Ljava/lang/Object;"
    INVOKEVIRTUAL java/lang/Object.equals (Ljava/lang/Object;)Z
    IFEQ L30
    ICONST_3
    IRETURN
   L9
    LDC "CGLIB$findMethodProxy(Lnet/sf/cglib/core/Signature;)Lnet/sf/cglib/proxy/MethodProxy;"
    INVOKEVIRTUAL java/lang/Object.equals (Ljava/lang/Object;)Z
    IFEQ L30
    BIPUSH 14
    IRETURN
   L10
    LDC "setCallbacks([Lnet/sf/cglib/proxy/Callback;)V"
    INVOKEVIRTUAL java/lang/Object.equals (Ljava/lang/Object;)Z
    IFEQ L30
    BIPUSH 6
    IRETURN
   L11
    LDC "CGLIB$showSelf$0()V"
    INVOKEVIRTUAL java/lang/Object.equals (Ljava/lang/Object;)Z
    IFEQ L30
    BIPUSH 16
    IRETURN
   L12
    LDC "wait(J)V"
    INVOKEVIRTUAL java/lang/Object.equals (Ljava/lang/Object;)Z
    IFEQ L30
    BIPUSH 24
    IRETURN
   L13
    LDC "setCallback(ILnet/sf/cglib/proxy/Callback;)V"
    INVOKEVIRTUAL java/lang/Object.equals (Ljava/lang/Object;)Z
    IFEQ L30
    BIPUSH 13
    IRETURN
   L14
    LDC "newInstance([Ljava/lang/Class;[Ljava/lang/Object;[Lnet/sf/cglib/proxy/Callback;)Ljava/lang/Object;"
    INVOKEVIRTUAL java/lang/Object.equals (Ljava/lang/Object;)Z
    IFEQ L30
    ICONST_5
    IRETURN
   L15
    LDC "notifyAll()V"
    INVOKEVIRTUAL java/lang/Object.equals (Ljava/lang/Object;)Z
    IFEQ L30
    BIPUSH 28
    IRETURN
   L16
    LDC "getCallbacks()[Lnet/sf/cglib/proxy/Callback;"
    INVOKEVIRTUAL java/lang/Object.equals (Ljava/lang/Object;)Z
    IFEQ L30
    BIPUSH 10
    IRETURN
   L17
    LDC "wait()V"
    INVOKEVIRTUAL java/lang/Object.equals (Ljava/lang/Object;)Z
    IFEQ L30
    BIPUSH 25
    IRETURN
   L18
    LDC "newInstance([Lnet/sf/cglib/proxy/Callback;)Ljava/lang/Object;"
    INVOKEVIRTUAL java/lang/Object.equals (Ljava/lang/Object;)Z
    IFEQ L30
    ICONST_4
    IRETURN
   L19
    LDC "getCallback(I)Lnet/sf/cglib/proxy/Callback;"
    INVOKEVIRTUAL java/lang/Object.equals (Ljava/lang/Object;)Z
    IFEQ L30
    BIPUSH 9
    IRETURN
   L20
    LDC "CGLIB$finalize$2()V"
    INVOKEVIRTUAL java/lang/Object.equals (Ljava/lang/Object;)Z
    IFEQ L30
    BIPUSH 18
    IRETURN
   L21
    LDC "CGLIB$SET_STATIC_CALLBACKS([Lnet/sf/cglib/proxy/Callback;)V"
    INVOKEVIRTUAL java/lang/Object.equals (Ljava/lang/Object;)Z
    IFEQ L30
    BIPUSH 7
    IRETURN
   L22
    LDC "CGLIB$toString$4()Ljava/lang/String;"
    INVOKEVIRTUAL java/lang/Object.equals (Ljava/lang/Object;)Z
    IFEQ L30
    BIPUSH 20
    IRETURN
   L23
    LDC "equals(Ljava/lang/Object;)Z"
    INVOKEVIRTUAL java/lang/Object.equals (Ljava/lang/Object;)Z
    IFEQ L30
    ICONST_0
    IRETURN
   L24
    LDC "notify()V"
    INVOKEVIRTUAL java/lang/Object.equals (Ljava/lang/Object;)Z
    IFEQ L30
    BIPUSH 27
    IRETURN
   L25
    LDC "CGLIB$show$1()V"
    INVOKEVIRTUAL java/lang/Object.equals (Ljava/lang/Object;)Z
    IFEQ L30
    BIPUSH 17
    IRETURN
   L26
    LDC "toString()Ljava/lang/String;"
    INVOKEVIRTUAL java/lang/Object.equals (Ljava/lang/Object;)Z
    IFEQ L30
    ICONST_1
    IRETURN
   L27
    LDC "hashCode()I"
    INVOKEVIRTUAL java/lang/Object.equals (Ljava/lang/Object;)Z
    IFEQ L30
    ICONST_2
    IRETURN
   L28
    LDC "show()V"
    INVOKEVIRTUAL java/lang/Object.equals (Ljava/lang/Object;)Z
    IFEQ L30
    BIPUSH 12
    IRETURN
   L29
    POP
   L30
    ICONST_M1
    IRETURN
    MAXSTACK = 2
    MAXLOCALS = 2

  // access flags 0x1
  public getIndex(Ljava/lang/String;[Ljava/lang/Class;)I
    ALOAD 1
    ALOAD 2
    SWAP
    DUP
    INVOKEVIRTUAL java/lang/Object.hashCode ()I
    LOOKUPSWITCH
      -2083498449: L0
      -1776922004: L1
      -1295482945: L2
      -1053468136: L3
      -1039689911: L4
      -338864151: L5
      -124978607: L6
      -60403779: L7
      -29025553: L8
      3529469: L9
      3641717: L10
      85179481: L11
      147696667: L12
      161998109: L13
      495524492: L14
      517345997: L15
      537463608: L16
      1154623345: L17
      1543336191: L18
      1811874389: L19
      1817099975: L20
      1902066072: L21
      1905679803: L22
      1950568386: L23
      1951977612: L24
      default: L25
   L0
    LDC "CGLIB$finalize$2"
    INVOKEVIRTUAL java/lang/Object.equals (Ljava/lang/Object;)Z
    IFEQ L26
    DUP
    ARRAYLENGTH
    TABLESWITCH
      0: L27
      default: L28
   L27
    POP
    BIPUSH 18
    IRETURN
   L28
    GOTO L29
   L1
    LDC "toString"
    INVOKEVIRTUAL java/lang/Object.equals (Ljava/lang/Object;)Z
    IFEQ L26
    DUP
    ARRAYLENGTH
    TABLESWITCH
      0: L30
      default: L31
   L30
    POP
    ICONST_1
    IRETURN
   L31
    GOTO L29
   L2
    LDC "equals"
    INVOKEVIRTUAL java/lang/Object.equals (Ljava/lang/Object;)Z
    IFEQ L26
    DUP
    ARRAYLENGTH
    TABLESWITCH
      1: L32
      default: L33
   L32
    DUP
    ICONST_0
    AALOAD
    INVOKEVIRTUAL java/lang/Class.getName ()Ljava/lang/String;
    LDC "java.lang.Object"
    INVOKEVIRTUAL java/lang/Object.equals (Ljava/lang/Object;)Z
    IFEQ L29
    POP
    ICONST_0
    IRETURN
   L33
    GOTO L29
   L3
    LDC "getCallbacks"
    INVOKEVIRTUAL java/lang/Object.equals (Ljava/lang/Object;)Z
    IFEQ L26
    DUP
    ARRAYLENGTH
    TABLESWITCH
      0: L34
      default: L35
   L34
    POP
    BIPUSH 10
    IRETURN
   L35
    GOTO L29
   L4
    LDC "notify"
    INVOKEVIRTUAL java/lang/Object.equals (Ljava/lang/Object;)Z
    IFEQ L26
    DUP
    ARRAYLENGTH
    TABLESWITCH
      0: L36
      default: L37
   L36
    POP
    BIPUSH 27
    IRETURN
   L37
    GOTO L29
   L5
    LDC "showSelf"
    INVOKEVIRTUAL java/lang/Object.equals (Ljava/lang/Object;)Z
    IFEQ L26
    DUP
    ARRAYLENGTH
    TABLESWITCH
      0: L38
      default: L39
   L38
    POP
    BIPUSH 11
    IRETURN
   L39
    GOTO L29
   L6
    LDC "CGLIB$equals$3"
    INVOKEVIRTUAL java/lang/Object.equals (Ljava/lang/Object;)Z
    IFEQ L26
    DUP
    ARRAYLENGTH
    TABLESWITCH
      1: L40
      default: L41
   L40
    DUP
    ICONST_0
    AALOAD
    INVOKEVIRTUAL java/lang/Class.getName ()Ljava/lang/String;
    LDC "java.lang.Object"
    INVOKEVIRTUAL java/lang/Object.equals (Ljava/lang/Object;)Z
    IFEQ L29
    POP
    BIPUSH 19
    IRETURN
   L41
    GOTO L29
   L7
    LDC "CGLIB$SET_STATIC_CALLBACKS"
    INVOKEVIRTUAL java/lang/Object.equals (Ljava/lang/Object;)Z
    IFEQ L26
    DUP
    ARRAYLENGTH
    TABLESWITCH
      1: L42
      default: L43
   L42
    DUP
    ICONST_0
    AALOAD
    INVOKEVIRTUAL java/lang/Class.getName ()Ljava/lang/String;
    LDC "[Lnet.sf.cglib.proxy.Callback;"
    INVOKEVIRTUAL java/lang/Object.equals (Ljava/lang/Object;)Z
    IFEQ L29
    POP
    BIPUSH 7
    IRETURN
   L43
    GOTO L29
   L8
    LDC "CGLIB$hashCode$5"
    INVOKEVIRTUAL java/lang/Object.equals (Ljava/lang/Object;)Z
    IFEQ L26
    DUP
    ARRAYLENGTH
    TABLESWITCH
      0: L44
      default: L45
   L44
    POP
    BIPUSH 21
    IRETURN
   L45
    GOTO L29
   L9
    LDC "show"
    INVOKEVIRTUAL java/lang/Object.equals (Ljava/lang/Object;)Z
    IFEQ L26
    DUP
    ARRAYLENGTH
    TABLESWITCH
      0: L46
      default: L47
   L46
    POP
    BIPUSH 12
    IRETURN
   L47
    GOTO L29
   L10
    LDC "wait"
    INVOKEVIRTUAL java/lang/Object.equals (Ljava/lang/Object;)Z
    IFEQ L26
    DUP
    ARRAYLENGTH
    TABLESWITCH
      0: L48
      1: L49
      2: L50
      default: L51
   L48
    POP
    BIPUSH 25
    IRETURN
   L49
    DUP
    ICONST_0
    AALOAD
    INVOKEVIRTUAL java/lang/Class.getName ()Ljava/lang/String;
    LDC "long"
    INVOKEVIRTUAL java/lang/Object.equals (Ljava/lang/Object;)Z
    IFEQ L29
    POP
    BIPUSH 24
    IRETURN
   L50
    DUP
    ICONST_0
    AALOAD
    INVOKEVIRTUAL java/lang/Class.getName ()Ljava/lang/String;
    LDC "long"
    INVOKEVIRTUAL java/lang/Object.equals (Ljava/lang/Object;)Z
    IFEQ L29
    DUP
    ICONST_1
    AALOAD
    INVOKEVIRTUAL java/lang/Class.getName ()Ljava/lang/String;
    LDC "int"
    INVOKEVIRTUAL java/lang/Object.equals (Ljava/lang/Object;)Z
    IFEQ L29
    POP
    BIPUSH 23
    IRETURN
   L51
    GOTO L29
   L11
    LDC "CGLIB$SET_THREAD_CALLBACKS"
    INVOKEVIRTUAL java/lang/Object.equals (Ljava/lang/Object;)Z
    IFEQ L26
    DUP
    ARRAYLENGTH
    TABLESWITCH
      1: L52
      default: L53
   L52
    DUP
    ICONST_0
    AALOAD
    INVOKEVIRTUAL java/lang/Class.getName ()Ljava/lang/String;
    LDC "[Lnet.sf.cglib.proxy.Callback;"
    INVOKEVIRTUAL java/lang/Object.equals (Ljava/lang/Object;)Z
    IFEQ L29
    POP
    BIPUSH 8
    IRETURN
   L53
    GOTO L29
   L12
    LDC "hashCode"
    INVOKEVIRTUAL java/lang/Object.equals (Ljava/lang/Object;)Z
    IFEQ L26
    DUP
    ARRAYLENGTH
    TABLESWITCH
      0: L54
      default: L55
   L54
    POP
    ICONST_2
    IRETURN
   L55
    GOTO L29
   L13
    LDC "CGLIB$STATICHOOK1"
    INVOKEVIRTUAL java/lang/Object.equals (Ljava/lang/Object;)Z
    IFEQ L26
    DUP
    ARRAYLENGTH
    TABLESWITCH
      0: L56
      default: L57
   L56
    POP
    BIPUSH 15
    IRETURN
   L57
    GOTO L29
   L14
    LDC "setCallbacks"
    INVOKEVIRTUAL java/lang/Object.equals (Ljava/lang/Object;)Z
    IFEQ L26
    DUP
    ARRAYLENGTH
    TABLESWITCH
      1: L58
      default: L59
   L58
    DUP
    ICONST_0
    AALOAD
    INVOKEVIRTUAL java/lang/Class.getName ()Ljava/lang/String;
    LDC "[Lnet.sf.cglib.proxy.Callback;"
    INVOKEVIRTUAL java/lang/Object.equals (Ljava/lang/Object;)Z
    IFEQ L29
    POP
    BIPUSH 6
    IRETURN
   L59
    GOTO L29
   L15
    LDC "CGLIB$show$1"
    INVOKEVIRTUAL java/lang/Object.equals (Ljava/lang/Object;)Z
    IFEQ L26
    DUP
    ARRAYLENGTH
    TABLESWITCH
      0: L60
      default: L61
   L60
    POP
    BIPUSH 17
    IRETURN
   L61
    GOTO L29
   L16
    LDC "CGLIB$showSelf$0"
    INVOKEVIRTUAL java/lang/Object.equals (Ljava/lang/Object;)Z
    IFEQ L26
    DUP
    ARRAYLENGTH
    TABLESWITCH
      0: L62
      default: L63
   L62
    POP
    BIPUSH 16
    IRETURN
   L63
    GOTO L29
   L17
    LDC "CGLIB$findMethodProxy"
    INVOKEVIRTUAL java/lang/Object.equals (Ljava/lang/Object;)Z
    IFEQ L26
    DUP
    ARRAYLENGTH
    TABLESWITCH
      1: L64
      default: L65
   L64
    DUP
    ICONST_0
    AALOAD
    INVOKEVIRTUAL java/lang/Class.getName ()Ljava/lang/String;
    LDC "net.sf.cglib.core.Signature"
    INVOKEVIRTUAL java/lang/Object.equals (Ljava/lang/Object;)Z
    IFEQ L29
    POP
    BIPUSH 14
    IRETURN
   L65
    GOTO L29
   L18
    LDC "CGLIB$toString$4"
    INVOKEVIRTUAL java/lang/Object.equals (Ljava/lang/Object;)Z
    IFEQ L26
    DUP
    ARRAYLENGTH
    TABLESWITCH
      0: L66
      default: L67
   L66
    POP
    BIPUSH 20
    IRETURN
   L67
    GOTO L29
   L19
    LDC "newInstance"
    INVOKEVIRTUAL java/lang/Object.equals (Ljava/lang/Object;)Z
    IFEQ L26
    DUP
    ARRAYLENGTH
    TABLESWITCH
      1: L68
      2: L69
      3: L70
      default: L69
   L68
    DUP
    ICONST_0
    AALOAD
    INVOKEVIRTUAL java/lang/Class.getName ()Ljava/lang/String;
    DUP
    INVOKEVIRTUAL java/lang/Object.hashCode ()I
    LOOKUPSWITCH
      -845341380: L71
      1730110032: L72
      default: L73
   L71
    LDC "net.sf.cglib.proxy.Callback"
    INVOKEVIRTUAL java/lang/Object.equals (Ljava/lang/Object;)Z
    IFEQ L74
    POP
    ICONST_3
    IRETURN
   L72
    LDC "[Lnet.sf.cglib.proxy.Callback;"
    INVOKEVIRTUAL java/lang/Object.equals (Ljava/lang/Object;)Z
    IFEQ L74
    POP
    ICONST_4
    IRETURN
   L73
    POP
   L74
    GOTO L29
   L70
    DUP
    ICONST_0
    AALOAD
    INVOKEVIRTUAL java/lang/Class.getName ()Ljava/lang/String;
    LDC "[Ljava.lang.Class;"
    INVOKEVIRTUAL java/lang/Object.equals (Ljava/lang/Object;)Z
    IFEQ L29
    DUP
    ICONST_1
    AALOAD
    INVOKEVIRTUAL java/lang/Class.getName ()Ljava/lang/String;
    LDC "[Ljava.lang.Object;"
    INVOKEVIRTUAL java/lang/Object.equals (Ljava/lang/Object;)Z
    IFEQ L29
    DUP
    ICONST_2
    AALOAD
    INVOKEVIRTUAL java/lang/Class.getName ()Ljava/lang/String;
    LDC "[Lnet.sf.cglib.proxy.Callback;"
    INVOKEVIRTUAL java/lang/Object.equals (Ljava/lang/Object;)Z
    IFEQ L29
    POP
    ICONST_5
    IRETURN
   L69
    GOTO L29
   L20
    LDC "setCallback"
    INVOKEVIRTUAL java/lang/Object.equals (Ljava/lang/Object;)Z
    IFEQ L26
    DUP
    ARRAYLENGTH
    TABLESWITCH
      2: L75
      default: L76
   L75
    DUP
    ICONST_0
    AALOAD
    INVOKEVIRTUAL java/lang/Class.getName ()Ljava/lang/String;
    LDC "int"
    INVOKEVIRTUAL java/lang/Object.equals (Ljava/lang/Object;)Z
    IFEQ L29
    DUP
    ICONST_1
    AALOAD
    INVOKEVIRTUAL java/lang/Class.getName ()Ljava/lang/String;
    LDC "net.sf.cglib.proxy.Callback"
    INVOKEVIRTUAL java/lang/Object.equals (Ljava/lang/Object;)Z
    IFEQ L29
    POP
    BIPUSH 13
    IRETURN
   L76
    GOTO L29
   L21
    LDC "notifyAll"
    INVOKEVIRTUAL java/lang/Object.equals (Ljava/lang/Object;)Z
    IFEQ L26
    DUP
    ARRAYLENGTH
    TABLESWITCH
      0: L77
      default: L78
   L77
    POP
    BIPUSH 28
    IRETURN
   L78
    GOTO L29
   L22
    LDC "getCallback"
    INVOKEVIRTUAL java/lang/Object.equals (Ljava/lang/Object;)Z
    IFEQ L26
    DUP
    ARRAYLENGTH
    TABLESWITCH
      1: L79
      default: L80
   L79
    DUP
    ICONST_0
    AALOAD
    INVOKEVIRTUAL java/lang/Class.getName ()Ljava/lang/String;
    LDC "int"
    INVOKEVIRTUAL java/lang/Object.equals (Ljava/lang/Object;)Z
    IFEQ L29
    POP
    BIPUSH 9
    IRETURN
   L80
    GOTO L29
   L23
    LDC "getClass"
    INVOKEVIRTUAL java/lang/Object.equals (Ljava/lang/Object;)Z
    IFEQ L26
    DUP
    ARRAYLENGTH
    TABLESWITCH
      0: L81
      default: L82
   L81
    POP
    BIPUSH 26
    IRETURN
   L82
    GOTO L29
   L24
    LDC "CGLIB$clone$6"
    INVOKEVIRTUAL java/lang/Object.equals (Ljava/lang/Object;)Z
    IFEQ L26
    DUP
    ARRAYLENGTH
    TABLESWITCH
      0: L83
      default: L84
   L83
    POP
    BIPUSH 22
    IRETURN
   L84
    GOTO L29
   L25
    POP
   L26
    GOTO L29
   L29
    POP
    ICONST_M1
    IRETURN
    MAXSTACK = 3
    MAXLOCALS = 3

  // access flags 0x1
  public getIndex([Ljava/lang/Class;)I
    ALOAD 1
    DUP
    ARRAYLENGTH
    TABLESWITCH
      0: L0
      default: L1
   L0
    POP
    ICONST_0
    IRETURN
   L1
    GOTO L2
   L2
    POP
    ICONST_M1
    IRETURN
    MAXSTACK = 2
    MAXLOCALS = 2

  // access flags 0x1
  public invoke(ILjava/lang/Object;[Ljava/lang/Object;)Ljava/lang/Object; throws java/lang/reflect/InvocationTargetException 
    TRYCATCHBLOCK L0 L1 L1 java/lang/Throwable
    ALOAD 2
    CHECKCAST com/java/core/proxy/cglib/RealSubject$$EnhancerByCGLIB$$be39b9b5
    ILOAD 1
   L0
    TABLESWITCH
      0: L2
      1: L3
      2: L4
      3: L5
      4: L6
      5: L7
      6: L8
      7: L9
      8: L10
      9: L11
      10: L12
      11: L13
      12: L14
      13: L15
      14: L16
      15: L17
      16: L18
      17: L19
      18: L20
      19: L21
      20: L22
      21: L23
      22: L24
      23: L25
      24: L26
      25: L27
      26: L28
      27: L29
      28: L30
      default: L31
   L2
    ALOAD 3
    ICONST_0
    AALOAD
    INVOKEVIRTUAL com/java/core/proxy/cglib/RealSubject$$EnhancerByCGLIB$$be39b9b5.equals (Ljava/lang/Object;)Z
    NEW java/lang/Boolean
    DUP_X1
    SWAP
    INVOKESPECIAL java/lang/Boolean.<init> (Z)V
    ARETURN
   L3
    INVOKEVIRTUAL com/java/core/proxy/cglib/RealSubject$$EnhancerByCGLIB$$be39b9b5.toString ()Ljava/lang/String;
    ARETURN
   L4
    INVOKEVIRTUAL com/java/core/proxy/cglib/RealSubject$$EnhancerByCGLIB$$be39b9b5.hashCode ()I
    NEW java/lang/Integer
    DUP_X1
    SWAP
    INVOKESPECIAL java/lang/Integer.<init> (I)V
    ARETURN
   L5
    ALOAD 3
    ICONST_0
    AALOAD
    CHECKCAST net/sf/cglib/proxy/Callback
    INVOKEVIRTUAL com/java/core/proxy/cglib/RealSubject$$EnhancerByCGLIB$$be39b9b5.newInstance (Lnet/sf/cglib/proxy/Callback;)Ljava/lang/Object;
    ARETURN
   L6
    ALOAD 3
    ICONST_0
    AALOAD
    CHECKCAST [Lnet/sf/cglib/proxy/Callback;
    INVOKEVIRTUAL com/java/core/proxy/cglib/RealSubject$$EnhancerByCGLIB$$be39b9b5.newInstance ([Lnet/sf/cglib/proxy/Callback;)Ljava/lang/Object;
    ARETURN
   L7
    ALOAD 3
    ICONST_0
    AALOAD
    CHECKCAST [Ljava/lang/Class;
    ALOAD 3
    ICONST_1
    AALOAD
    CHECKCAST [Ljava/lang/Object;
    ALOAD 3
    ICONST_2
    AALOAD
    CHECKCAST [Lnet/sf/cglib/proxy/Callback;
    INVOKEVIRTUAL com/java/core/proxy/cglib/RealSubject$$EnhancerByCGLIB$$be39b9b5.newInstance ([Ljava/lang/Class;[Ljava/lang/Object;[Lnet/sf/cglib/proxy/Callback;)Ljava/lang/Object;
    ARETURN
   L8
    ALOAD 3
    ICONST_0
    AALOAD
    CHECKCAST [Lnet/sf/cglib/proxy/Callback;
    INVOKEVIRTUAL com/java/core/proxy/cglib/RealSubject$$EnhancerByCGLIB$$be39b9b5.setCallbacks ([Lnet/sf/cglib/proxy/Callback;)V
    ACONST_NULL
    ARETURN
   L9
    ALOAD 3
    ICONST_0
    AALOAD
    CHECKCAST [Lnet/sf/cglib/proxy/Callback;
    INVOKESTATIC com/java/core/proxy/cglib/RealSubject$$EnhancerByCGLIB$$be39b9b5.CGLIB$SET_STATIC_CALLBACKS ([Lnet/sf/cglib/proxy/Callback;)V
    ACONST_NULL
    ARETURN
   L10
    ALOAD 3
    ICONST_0
    AALOAD
    CHECKCAST [Lnet/sf/cglib/proxy/Callback;
    INVOKESTATIC com/java/core/proxy/cglib/RealSubject$$EnhancerByCGLIB$$be39b9b5.CGLIB$SET_THREAD_CALLBACKS ([Lnet/sf/cglib/proxy/Callback;)V
    ACONST_NULL
    ARETURN
   L11
    ALOAD 3
    ICONST_0
    AALOAD
    CHECKCAST java/lang/Number
    INVOKEVIRTUAL java/lang/Number.intValue ()I
    INVOKEVIRTUAL com/java/core/proxy/cglib/RealSubject$$EnhancerByCGLIB$$be39b9b5.getCallback (I)Lnet/sf/cglib/proxy/Callback;
    ARETURN
   L12
    INVOKEVIRTUAL com/java/core/proxy/cglib/RealSubject$$EnhancerByCGLIB$$be39b9b5.getCallbacks ()[Lnet/sf/cglib/proxy/Callback;
    ARETURN
   L13
    INVOKEVIRTUAL com/java/core/proxy/cglib/RealSubject$$EnhancerByCGLIB$$be39b9b5.showSelf ()V
    ACONST_NULL
    ARETURN
   L14
    INVOKEVIRTUAL com/java/core/proxy/cglib/RealSubject$$EnhancerByCGLIB$$be39b9b5.show ()V
    ACONST_NULL
    ARETURN
   L15
    ALOAD 3
    ICONST_0
    AALOAD
    CHECKCAST java/lang/Number
    INVOKEVIRTUAL java/lang/Number.intValue ()I
    ALOAD 3
    ICONST_1
    AALOAD
    CHECKCAST net/sf/cglib/proxy/Callback
    INVOKEVIRTUAL com/java/core/proxy/cglib/RealSubject$$EnhancerByCGLIB$$be39b9b5.setCallback (ILnet/sf/cglib/proxy/Callback;)V
    ACONST_NULL
    ARETURN
   L16
    ALOAD 3
    ICONST_0
    AALOAD
    CHECKCAST net/sf/cglib/core/Signature
    INVOKESTATIC com/java/core/proxy/cglib/RealSubject$$EnhancerByCGLIB$$be39b9b5.CGLIB$findMethodProxy (Lnet/sf/cglib/core/Signature;)Lnet/sf/cglib/proxy/MethodProxy;
    ARETURN
   L17
    INVOKESTATIC com/java/core/proxy/cglib/RealSubject$$EnhancerByCGLIB$$be39b9b5.CGLIB$STATICHOOK1 ()V
    ACONST_NULL
    ARETURN
   L18
    INVOKEVIRTUAL com/java/core/proxy/cglib/RealSubject$$EnhancerByCGLIB$$be39b9b5.CGLIB$showSelf$0 ()V
    ACONST_NULL
    ARETURN
   L19
    INVOKEVIRTUAL com/java/core/proxy/cglib/RealSubject$$EnhancerByCGLIB$$be39b9b5.CGLIB$show$1 ()V
    ACONST_NULL
    ARETURN
   L20
    INVOKEVIRTUAL com/java/core/proxy/cglib/RealSubject$$EnhancerByCGLIB$$be39b9b5.CGLIB$finalize$2 ()V
    ACONST_NULL
    ARETURN
   L21
    ALOAD 3
    ICONST_0
    AALOAD
    INVOKEVIRTUAL com/java/core/proxy/cglib/RealSubject$$EnhancerByCGLIB$$be39b9b5.CGLIB$equals$3 (Ljava/lang/Object;)Z
    NEW java/lang/Boolean
    DUP_X1
    SWAP
    INVOKESPECIAL java/lang/Boolean.<init> (Z)V
    ARETURN
   L22
    INVOKEVIRTUAL com/java/core/proxy/cglib/RealSubject$$EnhancerByCGLIB$$be39b9b5.CGLIB$toString$4 ()Ljava/lang/String;
    ARETURN
   L23
    INVOKEVIRTUAL com/java/core/proxy/cglib/RealSubject$$EnhancerByCGLIB$$be39b9b5.CGLIB$hashCode$5 ()I
    NEW java/lang/Integer
    DUP_X1
    SWAP
    INVOKESPECIAL java/lang/Integer.<init> (I)V
    ARETURN
   L24
    INVOKEVIRTUAL com/java/core/proxy/cglib/RealSubject$$EnhancerByCGLIB$$be39b9b5.CGLIB$clone$6 ()Ljava/lang/Object;
    ARETURN
   L25
    ALOAD 3
    ICONST_0
    AALOAD
    CHECKCAST java/lang/Number
    INVOKEVIRTUAL java/lang/Number.longValue ()J
    ALOAD 3
    ICONST_1
    AALOAD
    CHECKCAST java/lang/Number
    INVOKEVIRTUAL java/lang/Number.intValue ()I
    INVOKEVIRTUAL com/java/core/proxy/cglib/RealSubject$$EnhancerByCGLIB$$be39b9b5.wait (JI)V
    ACONST_NULL
    ARETURN
   L26
    ALOAD 3
    ICONST_0
    AALOAD
    CHECKCAST java/lang/Number
    INVOKEVIRTUAL java/lang/Number.longValue ()J
    INVOKEVIRTUAL com/java/core/proxy/cglib/RealSubject$$EnhancerByCGLIB$$be39b9b5.wait (J)V
    ACONST_NULL
    ARETURN
   L27
    INVOKEVIRTUAL com/java/core/proxy/cglib/RealSubject$$EnhancerByCGLIB$$be39b9b5.wait ()V
    ACONST_NULL
    ARETURN
   L28
    INVOKEVIRTUAL com/java/core/proxy/cglib/RealSubject$$EnhancerByCGLIB$$be39b9b5.getClass ()Ljava/lang/Class;
    ARETURN
   L29
    INVOKEVIRTUAL com/java/core/proxy/cglib/RealSubject$$EnhancerByCGLIB$$be39b9b5.notify ()V
    ACONST_NULL
    ARETURN
   L30
    INVOKEVIRTUAL com/java/core/proxy/cglib/RealSubject$$EnhancerByCGLIB$$be39b9b5.notifyAll ()V
    ACONST_NULL
    ARETURN
   L31
    GOTO L32
   L1
    NEW java/lang/reflect/InvocationTargetException
    DUP_X1
    SWAP
    INVOKESPECIAL java/lang/reflect/InvocationTargetException.<init> (Ljava/lang/Throwable;)V
    ATHROW
   L32
    NEW java/lang/IllegalArgumentException
    DUP
    LDC "Cannot find matching method/constructor"
    INVOKESPECIAL java/lang/IllegalArgumentException.<init> (Ljava/lang/String;)V
    ATHROW
    MAXSTACK = 5
    MAXLOCALS = 4

  // access flags 0x1
  public newInstance(I[Ljava/lang/Object;)Ljava/lang/Object; throws java/lang/reflect/InvocationTargetException 
    TRYCATCHBLOCK L0 L1 L1 java/lang/Throwable
    NEW com/java/core/proxy/cglib/RealSubject$$EnhancerByCGLIB$$be39b9b5
    DUP
    ILOAD 1
   L0
    TABLESWITCH
      0: L2
      default: L3
   L2
    INVOKESPECIAL com/java/core/proxy/cglib/RealSubject$$EnhancerByCGLIB$$be39b9b5.<init> ()V
    ARETURN
   L3
    GOTO L4
   L1
    NEW java/lang/reflect/InvocationTargetException
    DUP_X1
    SWAP
    INVOKESPECIAL java/lang/reflect/InvocationTargetException.<init> (Ljava/lang/Throwable;)V
    ATHROW
   L4
    NEW java/lang/IllegalArgumentException
    DUP
    LDC "Cannot find matching method/constructor"
    INVOKESPECIAL java/lang/IllegalArgumentException.<init> (Ljava/lang/String;)V
    ATHROW
    MAXSTACK = 5
    MAXLOCALS = 3

  // access flags 0x1
  public getMaxIndex()I
    BIPUSH 28
    IRETURN
    MAXSTACK = 1
    MAXLOCALS = 1
}
